dbmap/__init__.py
dbmap/ann.py
dbmap/diffusion.py
dbmap/distances.py
dbmap/graph_utils.py
dbmap/layout.py
dbmap/map.py
dbmap/multiscale.py
dbmap/pacmapper.py
dbmap/plot.py
dbmap/spectral.py
dbmap/umap_layouts.py
dbmap/utils.py
dbmap/version.py
dbmap-1.2.0.4.dist-info/LICENSE
dbmap-1.2.0.4.dist-info/METADATA
dbmap-1.2.0.4.dist-info/WHEEL
dbmap-1.2.0.4.dist-info/top_level.txt
dbmap-1.2.0.4.dist-info/RECORD
