Metadata-Version: 2.1
Name: dbmap
Version: 1.2.0.4
Summary: dbMAP: diffusion metrics, graphs and layouts for machine-learning
Home-page: https://github.com/davisidarta/dbMAP
Author: Davi Sidarta-Oliveira
Author-email: davisidarta@fcm.unicamp.br
License: UNKNOWN
Project-URL: Bug Tracker, https://github.com/davisidarta/dbMAP/issues
Platform: UNKNOWN
Classifier: Programming Language :: Python :: 3
Classifier: License :: OSI Approved :: GNU General Public License v2 (GPLv2)
Classifier: Operating System :: OS Independent
Requires-Python: >=3.6
